{
  "version": "1.0.0",
  "templates": {
    "go": {
      "url": "https://gitlab.51zcm.cc/go/util",
      "branch": "master",
      "description": "go 模板"
    }, 
    "eggjs": {
      "url": "https://gitlab.51zcm.cc/front/service",
      "branch": "test",
      "description": "eggjs S端模板",
      "replace": {
        "variables": {
          "spaceName": "微服务空间名",
          "k8sServerName": "服务名",
          "dockerRegistryNamespace": "docker空间名"
        },
        "paths": [
          "Jenkinsfile",
          "package.json",
          "build.sh"
        ]
      }
    }
  }
}